rag_lecture/__init__.py
rag_lecture/core.py
rag_lecture/utils.py
rag_lecture-0.1.1.dist-info/licenses/LICENSE
rag_lecture-0.1.1.dist-info/METADATA
rag_lecture-0.1.1.dist-info/WHEEL
rag_lecture-0.1.1.dist-info/top_level.txt
rag_lecture-0.1.1.dist-info/RECORD
